{
  "id": "1764759",
  "name": "冬青",
  "font_family": "iconfont",
  "css_prefix_text": "icon-",
  "description": "",
  "glyphs": [
    {
      "icon_id": "14846193",
      "name": "龟背竹",
      "font_class": "2",
      "unicode": "e623",
      "unicode_decimal": 58915
    },
    {
      "icon_id": "14846262",
      "name": "绿植1",
      "font_class": "lvzhi1",
      "unicode": "e624",
      "unicode_decimal": 58916
    },
    {
      "icon_id": "14871017",
      "name": "绿植3",
      "font_class": "lvzhi3",
      "unicode": "e629",
      "unicode_decimal": 58921
    },
    {
      "icon_id": "14871018",
      "name": "绿植4",
      "font_class": "lvzhi4",
      "unicode": "e62a",
      "unicode_decimal": 58922
    },
    {
      "icon_id": "14871019",
      "name": "绿植8",
      "font_class": "lvzhi8",
      "unicode": "e62b",
      "unicode_decimal": 58923
    },
    {
      "icon_id": "14871020",
      "name": "绿植6",
      "font_class": "lvzhi6",
      "unicode": "e62c",
      "unicode_decimal": 58924
    },
    {
      "icon_id": "14871021",
      "name": "绿植10",
      "font_class": "lvzhi10",
      "unicode": "e62d",
      "unicode_decimal": 58925
    },
    {
      "icon_id": "14871022",
      "name": "绿植14",
      "font_class": "lvzhi14",
      "unicode": "e62e",
      "unicode_decimal": 58926
    },
    {
      "icon_id": "14871023",
      "name": "绿植11",
      "font_class": "lvzhi11",
      "unicode": "e62f",
      "unicode_decimal": 58927
    },
    {
      "icon_id": "14871024",
      "name": "绿植12",
      "font_class": "lvzhi12",
      "unicode": "e630",
      "unicode_decimal": 58928
    },
    {
      "icon_id": "14871025",
      "name": "绿植13",
      "font_class": "lvzhi13",
      "unicode": "e631",
      "unicode_decimal": 58929
    },
    {
      "icon_id": "411687",
      "name": "15",
      "font_class": "15",
      "unicode": "e61e",
      "unicode_decimal": 58910
    },
    {
      "icon_id": "485856",
      "name": "7",
      "font_class": "7",
      "unicode": "e633",
      "unicode_decimal": 58931
    },
    {
      "icon_id": "608356",
      "name": "箭头",
      "font_class": "jiantouarrow491",
      "unicode": "e6af",
      "unicode_decimal": 59055
    },
    {
      "icon_id": "630128",
      "name": "照相机",
      "font_class": "zhaoxiangji",
      "unicode": "e663",
      "unicode_decimal": 58979
    },
    {
      "icon_id": "755545",
      "name": "箭头",
      "font_class": "right-arrow",
      "unicode": "e627",
      "unicode_decimal": 58919
    },
    {
      "icon_id": "947131",
      "name": "坐标",
      "font_class": "zuobiao",
      "unicode": "e679",
      "unicode_decimal": 59001
    },
    {
      "icon_id": "1245556",
      "name": "购物车",
      "font_class": "gouwuche",
      "unicode": "e655",
      "unicode_decimal": 58965
    },
    {
      "icon_id": "1371929",
      "name": "箭头",
      "font_class": "jiantou",
      "unicode": "e636",
      "unicode_decimal": 58934
    },
    {
      "icon_id": "1695404",
      "name": "菜单",
      "font_class": "caidan",
      "unicode": "e604",
      "unicode_decimal": 58884
    },
    {
      "icon_id": "2678579",
      "name": "菜单",
      "font_class": "caidan1",
      "unicode": "e63d",
      "unicode_decimal": 58941
    },
    {
      "icon_id": "5194501",
      "name": "照相机 相机",
      "font_class": "wenjuicon",
      "unicode": "e602",
      "unicode_decimal": 58882
    },
    {
      "icon_id": "5924468",
      "name": "搜索",
      "font_class": "sousuo",
      "unicode": "e61c",
      "unicode_decimal": 58908
    },
    {
      "icon_id": "6756285",
      "name": "菜单",
      "font_class": "caidan2",
      "unicode": "e605",
      "unicode_decimal": 58885
    },
    {
      "icon_id": "11019861",
      "name": "维修",
      "font_class": "weixiu",
      "unicode": "e60e",
      "unicode_decimal": 58894
    }
  ]
}
